odoo/addons/mgmtsystem_nonconformity_type/README.rst
odoo/addons/mgmtsystem_nonconformity_type/__init__.py
odoo/addons/mgmtsystem_nonconformity_type/__manifest__.py
odoo/addons/mgmtsystem_nonconformity_type/data/mgmtsystem_nonconformity_mail_data.xml
odoo/addons/mgmtsystem_nonconformity_type/i18n/es.po
odoo/addons/mgmtsystem_nonconformity_type/i18n/it.po
odoo/addons/mgmtsystem_nonconformity_type/i18n/mgmtsystem_nonconformity_type.pot
odoo/addons/mgmtsystem_nonconformity_type/models/__init__.py
odoo/addons/mgmtsystem_nonconformity_type/models/mgmtsystem_nonconformity.py
odoo/addons/mgmtsystem_nonconformity_type/readme/CONTRIBUTORS.rst
odoo/addons/mgmtsystem_nonconformity_type/readme/DESCRIPTION.rst
odoo/addons/mgmtsystem_nonconformity_type/readme/HISTORY.rst
odoo/addons/mgmtsystem_nonconformity_type/readme/ROADMAP.rst
odoo/addons/mgmtsystem_nonconformity_type/readme/USAGE.rst
odoo/addons/mgmtsystem_nonconformity_type/static/description/icon.png
odoo/addons/mgmtsystem_nonconformity_type/static/description/index.html
odoo/addons/mgmtsystem_nonconformity_type/tests/__init__.py
odoo/addons/mgmtsystem_nonconformity_type/tests/test_nonconformity_type.py
odoo/addons/mgmtsystem_nonconformity_type/views/mgmtsystem_nonconformity_views.xml
odoo14_addon_mgmtsystem_nonconformity_type-14.0.1.0.1.dev11.dist-info/METADATA
odoo14_addon_mgmtsystem_nonconformity_type-14.0.1.0.1.dev11.dist-info/WHEEL
odoo14_addon_mgmtsystem_nonconformity_type-14.0.1.0.1.dev11.dist-info/top_level.txt
odoo14_addon_mgmtsystem_nonconformity_type-14.0.1.0.1.dev11.dist-info/RECORD
